<?xml version="1.0"?>
<Items>
    <Item Name="Blank Rune" Kind="Tool" ID="HC4B"/>
	<Item Name="Ultimate Healing Rune" Kind="Rune" ID="HC58"/>
    <Item Name="Intense Healing Rune" Kind="Rune" ID="HC50"/>
    <Item Name="Sudden Death Rune" Kind="Rune" ID="HC53"/>
    <Item Name="Blank Rune" Kind="Tool" ID="HC4B"/>
    <Item Name="Heavy Magic Missile Rune" Kind="Rune" ID="HC7E"/>
    <Item Name="Destroy Field Rune" Kind="Rune" ID="HC4C"/>
    <Item Name="Energy Field Rune" Kind="Rune" ID="HC5C"/>
    <Item Name="Fire Field Rune" Kind="Rune" ID="HC74"/>
	<Item Name="Fireball Rune" Kind="Rune" ID="HC75"/>
    <Item Name="Explosion Rune" Kind="Rune" ID="HC80"/>
    <Item Name="Convince Creature Rune" Kind="Rune" ID="HC69"/>
    <Item Name="Great Fireball Rune" Kind="Rune" ID="HC77"/>
    <Item Name="Light Magic Missile Rune" Kind="Rune" ID="HC66"/>
    <Item Name="Poison Field Rune" Kind="Rune" ID="HC64"/>
    <Item Name="Chameleon Rune" Kind="Rune" ID="HC6A"/>
    <Item Name="Antidote Rune" Kind="Rune" ID="HC51"/>
    <Item Name="Firebomb Rune" Kind="Rune" ID="HC78"/>
    <Item Name="Poison Wall Rune" Kind="Rune" ID="HC68"/>
    <Item Name="Energy Wall Rune" Kind="Rune" ID="HC5E"/>
    <Item Name="Fire Wall Rune" Kind="Rune" ID="HC76"/>
	<Item Name="Paralyze Rune" Kind="Rune" ID="HC5D"/>
	
    <Item Name="Fish" Kind="Food" ID="Hdfa"/>
    <Item Name="Ham" Kind="Food" ID="Hdfe"/>
    <Item Name="Meat" Kind="Food" ID="Hdf9"/>
    <Item Name="White Mushroom" Kind="Food" ID="He8b"/>
    <Item Name="Apple" Kind="Food" ID="He01"/>
    <Item Name="Brown Mushroom" Kind="Food" ID="He8d"/>
    <Item Name="Banana" Kind="Food" ID="He03"/>
    <Item Name="Dragon Ham" Kind="Food" ID="Hdff"/>
    <Item Name="Blueberry" Kind="Food" ID="He04"/>
    <Item Name="Bread" Kind="Food" ID="He10"/>
    <Item Name="Brown Bread" Kind="Food" ID="He12"/>
    <Item Name="Carrot" Kind="Food" ID="He0b"/>
    <Item Name="Cheese" Kind="Food" ID="He17"/>
    <Item Name="Coconut" Kind="Food" ID="He05"/>
    <Item Name="Corncob" Kind="Food" ID="He0d"/>
    <Item Name="Green Mushroom" Kind="Food" ID="He94"/>
    <Item Name="Roll" Kind="Food" ID="He11"/>
    <Item Name="Salmon" Kind="Food" ID="Hdfb"/>
    <Item Name="Rope" Kind="Tool" ID="HBBB"/>
    <Item Name="Shovel" Kind="Tool" ID="HD81"/>
    <Item Name="Light Shovel" Kind="Tool" ID="H164E" />
    <Item Name="Fishing Rod" Kind="Tool" ID="HD9B"/>
    <Item Name="Machete" Kind="Equipment,SingleHandedWeapon,Tool" ID="3308"/>
    <Item Name="Crowbar" Kind="Equipment,SingleHandedWeapon,Tool" ID="HCE8"/>
    <Item Name="Rake" Kind="Tool" ID="HD7C"/>
    <Item Name="Pick" Kind="Tool" ID="HD80"/>
    <Item Name="Scythe" Kind="Equipment,SingleHandedWeapon,Tool" ID="HD7D"/>
    <Item Name="Magic Light Wand" Kind="Tool,LightSource" ID="HBE6"/>
    <Item Name="Light Shovel" Kind="Tool" ID="H164E"/>
    <Item Name="Spear" Kind="Equipment,SingleHandedWeapon,Throwable" ID="HCCD"/>
    <Item Name="Small Stone" Kind="Equipment,SingleHandedWeapon,Throwable" ID="H6F5"/>
    <Item Name="Throwing Star" Kind="Equipment,SingleHandedWeapon,Throwable" ID="HCD7"/>
    <Item Name="Throwing Knife" Kind="Equipment,SingleHandedWeapon,Throwable" ID="HCE2"/>
    <Item Name="Snowball" Kind="Equipment,SingleHandedWeapon,Throwable" ID="HBB0"/>        
    
    <Item Name="Gray Backpack" Kind="Equipment,Container" ID="2870"/>
    <Item Name="Purple Backpack" Kind="Equipment,Container" ID="2868"/>
    <Item Name="Golden Backpack" Kind="Equipment,Container" ID="2871"/>
    <Item Name="Jungle Backpack" Kind="Equipment,Container" ID="2872"/>
    <Item Name="Yellow Backpack" Kind="Equipment,Container" ID="2866"/>
    <Item Name="Red Backpack" Kind="Equipment,Container" ID="2867"/>
    <Item Name="Brown Backpack" Kind="Equipment,Container" ID="2854"/>
    <Item Name="Green Backpack" Kind="Equipment,Container" ID="2865"/>
    <Item Name="Blue Backpack" Kind="Equipment,Container" ID="2869"/>
    <Item Name="Pirate Backpack" Kind="Equipment,Container" ID="5926"/>
    <Item Name="Star Backpack" Kind="Equipment,Container" ID="5949"/>
    <Item Name="Brown Bag" Kind="Equipment,Container" ID="HB25"/>
    <Item Name="Pirate Bag" Kind="Equipment,Container" ID="H1727"/>
    <Item Name="Star Bag" Kind="Equipment,Container" ID="H173E"/>
    <Item Name="Green Bag" Kind="Equipment,Container" ID="2857"/>
    <Item Name="Yellow Bag" Kind="Equipment,Container" ID="2858"/>
    <Item Name="Red Bag" Kind="Equipment,Container" ID="2859"/>
    <Item Name="Purple Bag" Kind="Equipment,Container" ID="2860"/>
    <Item Name="Blue Bag" Kind="Equipment,Container" ID="2861"/>
    <Item Name="Gray Bag" Kind="Equipment,Container" ID="2862"/>
    <Item Name="Golden Bag" Kind="Equipment,Container" ID="2863"/>
    <Item Name="Jungle Bag" Kind="Equipment,Container" ID="2864"/>
    <Item Name="Backpack Of Holding" Kind="Equipment,Container" ID="3253"/>
    <Item Name="Parcel" Kind="Container" ID="3503"/>
    <Item Name="Present" Kind="Container" ID="2856" />
    <Item Name="Stamped Parcel" Kind="Container" ID="3504"/>
    <Item Name="Chest" Kind="Container,Blocking" ID="2472"/>
    <Item Name="Basket" Kind="Container" ID="2855"/>
    <Item Name="Crate" Kind="Container,Blocking" ID="2471"/>
    <Item Name="Brown Box" Kind="Container,Blocking" ID="2473"/>
    <Item Name="Chest" Kind="Container,Blocking" ID="2480"/>
    <Item Name="Chest" Kind="Container,Blocking" ID="2481"/>
    <Item Name="Chest" Kind="Container,Blocking" ID="2482"/>    
    <Item Name="Box" Kind="Container,Blocking" ID="2469"/>
    <Item Name="Drawer" Kind="Container,Blocking" ID="2431"/>
    <Item Name="Drawer" Kind="Container,Blocking" ID="2432"/>
    <Item Name="Drawer" Kind="Container,Blocking" ID="2433"/>
    <Item Name="Drawer" Kind="Container,Blocking" ID="2434"/>   
    <Item Name="Booshelf" Kind="Container,Blocking" ID="2435"/>
    <Item Name="Booshelf" Kind="Container,Blocking" ID="2436"/>
    <Item Name="Booshelf" Kind="Container,Blocking" ID="2437"/>
    <Item Name="Booshelf" Kind="Container,Blocking" ID="2438"/>
    <Item Name="Booshelf" Kind="Container,Blocking" ID="2439"/>
    <Item Name="Booshelf" Kind="Container,Blocking" ID="2440"/>
    <Item Name="Drawer" Kind="Container,Blocking" ID="2441"/>
    <Item Name="Drawer" Kind="Container,Blocking" ID="2442"/>
    <Item Name="Drawer" Kind="Container,Blocking" ID="2443"/>
    <Item Name="Drawer" Kind="Container,Blocking" ID="2444"/>    
    <Item Name="Locker" Kind="Container,Blocking" ID="2449"/>
    <Item Name="Locker" Kind="Container,Blocking" ID="2450"/>
    <Item Name="Locker" Kind="Container,Blocking" ID="2451"/>
    <Item Name="Locker" Kind="Container,Blocking" ID="2452"/>
    <Item Name="Drawer" Kind="Container,Blocking" ID="2465"/>
    <Item Name="Drawer" Kind="Container,Blocking" ID="2466"/>
    <Item Name="Drawer" Kind="Container,Blocking" ID="2467"/>    
    <Item Name="Drawer" Kind="Container,Blocking" ID="2468"/>    
    <Item Name="Box" Kind="Container,FullBlocking" ID="2483"/>
    <Item Name="Box" Kind="Container,FullBlocking" ID="2484"/>
    <Item Name="Box" Kind="Container,FullBlocking" ID="2485"/>
    <Item Name="Box" Kind="Container,FullBlocking" ID="2486"/>
    <Item Name="Barrel" Kind="Container,FullBlocking" ID="2520"/>
    <Item Name="Barrel" Kind="Container,FullBlocking" ID="2523"/>
    <Item Name="Trough" Kind="FluidContainer,FullBlocking" ID="2524"/>
    
    <Item Name="Treasure Chest With Gold" Kind="FullBlocking,Special" ID="5675" />
    <Item Name="Botanist's Container" Kind="Valuable" ID="4869" />
    <Item Name="Jewel Case" Kind="Equipment,Container" ID="6104"/>
    <Item Name="Worm" Kind="Tool" ID="HDA4"/>
    <Item Name="Remains Of A Ghost" Kind="Container" ID="H10c2"/>

    <Item Name="Depot" Kind="Container" ID="HDAE"/>
    <Item Name="Depot" Kind="Container" ID="HDAB"/>
    <Item Name="Depot" Kind="Container" ID="HDAA"/>
    <Item Name="Depot" Kind="Container" ID="HDA9"/>
    <Item Name="Depot" Kind="Container" ID="HDAC"/>
    <Item Name="Teleport" Kind="Teleport" ID="H79D"/>
    <Item Name="Ladder" Kind="UsableTeleport" ID="H79C"/>
    <Item Name="Ladder" Kind="UsableTeleport" ID="H7B0"/>
    <Item Name="Mailbox" Kind="Special" ID="HDAD"/>
    <Item Name="Closed H. Door1" Kind="Door" ID="H14A3"/>
    <Item Name="Closed H. Door2" Kind="Door" ID="H14A5"/>
    <Item Name="Closed H. Door3" Kind="Door" ID="H1870"/>
    <Item Name="Closed H. Door4" Kind="Door" ID="H186E"/>
    <Item Name="Closed H. Door5" Kind="Door" ID="H13DA"/>
    <Item Name="Closed H. Door6" Kind="Door" ID="H13F5"/>
    <Item Name="Open H. Door1" Kind="Door" ID="H1871"/>
    <Item Name="Open H. Door2" Kind="Door" ID="H1838"/>
    <Item Name="Open H. Door3" Kind="Door" ID="H14A4"/>
    <Item Name="Open H. Door4" Kind="Door" ID="H14A6"/>
    <Item Name="Open H. Door5" Kind="Door" ID="H667"/>
    <Item Name="Open H. Door6" Kind="Door" ID="H669"/>        
    <Item Name="Open H. Door7" Kind="Door" ID="H186F"/>  
    <Item Name="Open H. Door8" Kind="Door" ID="H13DB"/>  
    <Item Name="Closed H. Door7" Kind="Door" ID="H13F6"/>
    <Item Name="Closed Door1" Kind="Door" ID="H685"/>
    <Item Name="Closed Door2" Kind="Door" ID="H1404"/>
    <Item Name="Closed Door3" Kind="Door" ID="H149D"/>
    <Item Name="Closed Door4" Kind="Door" ID="H14A0"/>
    <Item Name="Closed Door5" Kind="Door" ID="H13FD"/>
    <Item Name="Closed Door6" Kind="Door" ID="H65D"/>
    <Item Name="Closed Door7" Kind="Door" ID="H660"/>
    <Item Name="Closed Door8" Kind="Door" ID="H699"/>
    <Item Name="Closed Door9" Kind="Door" ID="H1330"/>
    <Item Name="Closed DoorA" Kind="Door" ID="H13F2"/>
    <Item Name="Open Door1" Kind="Door" ID="H686"/>
    <Item Name="Open Door2" Kind="Door" ID="H1406"/>
    <Item Name="Open Door3" Kind="Door" ID="H149F"/>
    <Item Name="Open Door4" Kind="Door" ID="H14A2"/>
    <Item Name="Open Door5" Kind="Door" ID="H13BF"/>
    <Item Name="Open Door6" Kind="Door" ID="H132F"/>
    <Item Name="Open Door7" Kind="Door" ID="H13F4"/>
    <Item Name="Open Door8" Kind="Door" ID="H65E"/>
    <Item Name="Open Door9" Kind="Door" ID="H661"/>
    <Item Name="Open DoorA" Kind="Door" ID="H689"/>
    <Item Name="Locked Door1" Kind="Door" ID="H684"/>
    <Item Name="Locked Door2" Kind="Door" ID="H1405"/>
    <Item Name="Locked Door3" Kind="Door" ID="H13EA"/>
    <Item Name="Down1" Kind="Teleport" ID="H1D5"/>
    <Item Name="Down2" Kind="Teleport" ID="H1B2"/>
    <Item Name="Down3" Kind="Teleport" ID="H1B1"/>
    <Item Name="Down4" Kind="UsableTeleport2" ID="H1B3"/>
    <Item Name="Down5" Kind="UsableTeleport2" ID="H253"/> 
    <Item Name="Down6" Kind="Teleport" ID="H1B0"/>
    <Item Name="Down7" Kind="Teleport" ID="H1B6"/>
    <Item Name="Down8" Kind="Teleport" ID="H19B"/>
    <Item Name="Down9" Kind="Teleport" ID="H1E2"/>
    <Item Name="DownA" Kind="Teleport" ID="H163B"/>
    <Item Name="DownB" Kind="Teleport" ID="H19D"/>
    <Item Name="Stairs1" Kind="Teleport" ID="H79B"/>
    <Item Name="Stairs2" Kind="Teleport" ID="H7A6"/>
    <Item Name="Stairs3" Kind="Teleport" ID="H148A"/>
    <Item Name="Stairs4" Kind="Teleport" ID="H148B"/>
    <Item Name="Water With Fish1" Kind="FullBlocking" ID="H11F5"/>
    <Item Name="Water With Fish2" Kind="FullBlocking" ID="H11F6"/>
    <Item Name="Water With Fish3" Kind="FullBlocking" ID="H11F7"/>
    <Item Name="Water With Fish4" Kind="FullBlocking" ID="H11F8"/>
    <Item Name="Water With Fish5" Kind="FullBlocking" ID="H11F9"/>
    <Item Name="Water With Fish6" Kind="FullBlocking" ID="H11FA"/>
    <Item Name="Water1" Kind="FullBlocking" ID="H1201"/>
    <Item Name="Water2" Kind="FullBlocking" ID="H1202"/>
    <Item Name="Water3" Kind="FullBlocking" ID="H1203"/>
    <Item Name="Water4" Kind="FullBlocking" ID="H1204"/>
    <Item Name="Water5" Kind="FullBlocking" ID="H1205"/>
    <Item Name="Water6" Kind="FullBlocking" ID="H1206"/>
    <Item Name="Downstairs" Kind="Teleport" ID="H1B5"/>        
    <Item Name="Dustbin" Kind="Special" ID="H9DE"/>
    <Item Name="Vial" Kind="FluidContainer" ID="HB3A"/>
    <Item Name="King Voodoo Doll" Kind="Valuable" ID="HC89"/>    
    <Item Name="Post Horn" Kind="Valuable" ID="HB8D"/>
    <Item Name="Platinum Coin" Kind="Valuable" ID="HBDB"/>
    <Item Name="Crystal Coin" Kind="Valuable" ID="HBE3"/>
    <Item Name="Bright Sword" Kind="Equipment,SingleHandedWeapon,Tool" ID="HCDF"/>
    <Item Name="Royal Helmet" Kind="Equipment,Helmet" ID="HD40"/>
    <Item Name="Golden Armor" Kind="Armor" ID="HD20"/>
	<Item Name="Krimhorn Helmet" Kind="Equipment,Helmet" ID="H198"/>
	<Item Name="Giant Sword" Kind="Equipment,DoubleHandedWeapon,Tool" ID="HCD1"/>
    <Item Name="Crown Legs" Kind="Equipment,Leg" ID="HD36"/>
    <Item Name="Boots Of Haste" Kind="Equipment,Footwear" ID="HC07"/>
    <Item Name="Demon Shield" Kind="Equipment,Shield" ID="HD5C"/>
    <Item Name="Combat Knife" Kind="Equipment,SingleHandedWeapon,Tool" ID="HCDC"/>
    <Item Name="Knife" Kind="Equipment,SingleHandedWeapon,Tool" ID="HCDB"/>
    <Item Name="Crocodile Boots" Kind="Equipment,Footwear" ID="HDE4"/>
    <Item Name="Two Handed Sword" Kind="DoubleHandedWeapon,Tool" ID="HCC1"/>
    <Item Name="Silver Key 3033" Kind="Valuable" ID="HB99"/>
    <Item Name="Soldier Helmet" Kind="Equipment,Helmet" ID="HD19"/>
    <Item Name="Dwarven Shield" Kind="Equipment,Shield" ID="HD61"/>
    <Item Name="Plate Armor" Kind="Equipment,Armor" ID="HD1D"/>
    <Item Name="Plate Legs" Kind="Equipment,Leg" ID="HDE5"/>
    <Item Name="Leather Boots" Kind="Equipment,Footwear" ID="HDE0"/>
    <Item Name="Steel Helmet" Kind="Equipment,Helmet" ID="HD17"/>
    <Item Name="Tortoise Shield" Kind="Equipment,Shield" ID="H17F3"/>
    <Item Name="Bow" Kind="Equipment,DoubleHandedWeapon" ID="HD16"/>
    <Item Name="Crown Armor" Kind="Equipment,Armor" ID="HD35"/>
    <Item Name="Crown Helmet" Kind="Equipment,Helmet" ID="HD1D"/>
    <Item Name="Chain Legs" Kind="Equipment,Leg" ID="HDE6"/>
    <Item Name="Cream Cake" Kind="Valuable" ID="H18F9"/>
    <Item Name="Sandals" Kind="Equipment,Footwear" ID="HDDF"/>
    <Item Name="Pot" Kind="FluidContainer,FullBlocking" ID="HD89"/>
    <Item Name="Candelabrum" Kind="LightSource" ID="HB5F"/>
    <Item Name="Lit Candelabrum" Kind="LightSource" ID="HB60"/>
    <Item Name="Parchment" Kind="Tool" ID="HB13"/>
    <Item Name="Lyre" Kind="Valuable" ID="HB85"/>
    <Item Name="Party Trumpet" Kind="Valuable" ID="H19AC"/>
    <Item Name="Wooden Doll" Kind="Valuable" ID="HBAD"/>
    <Item Name="Small Diamond" Kind="Valuable" ID="HBD4"/>
    <Item Name="Silver Brooch" Kind="Valuable" ID="HBC9"/>
    <Item Name="White Tapestry" Kind="Valuable" ID="HA6B"/>
    <Item Name="Blue Tapestry" Kind="Valuable" ID="HA63"/>
    <Item Name="Furniture Package" Kind="Valuable" ID="HAE1"/>
    <Item Name="Furniture Package" Kind="Valuable" ID="HADB"/>
    <Item Name="Party Hat" Kind="Equipment,Helmet" ID="H19B2"/>
    <Item Name="Blue Robe" Kind="Equipment,Armor" ID="HDEF"/>
    <Item Name="Dark Helmet" Kind="Equipment,Helmet" ID="HD38"/>
    <Item Name="Amulet of Loss" Kind="Equipment,Neck" ID="HBF1"/>
    <Item Name="Star Amulet" Kind="Equipment,Neck" ID="HBC6"/>
    <Item Name="Scarf" Kind="Equipment,Neck" ID="HDF4"/>
    <Item Name="Wolf Tooth Chain" Kind="Equipment,Neck" ID="HBC4"/>
    <Item Name="Stone Skin Amulet" Kind="Equipment,Neck" ID="HC09"/>
    <Item Name="Elven Amulet" Kind="Equipment,Neck" ID="HC0A"/>
    <Item Name="Crystal Necklace" Kind="Equipment,Neck" ID="HBC0"/>
    <Item Name="Protection Amulet" Kind="Equipment,Neck" ID="HC0C"/>
    <Item Name="Silver Amulet" Kind="Equipment,Neck" ID="HBEE"/>
    <Item Name="Strange Talisman" Kind="Equipment,Neck" ID="HBE5"/>
    <Item Name="Garlick Necklace" Kind="Equipment,Neck" ID="HC0B"/>
    <Item Name="Bronze Amulet" Kind="Equipment,Neck" ID="HBF0"/>
    <Item Name="Dragon Necklace" Kind="Equipment,Neck" ID="HC0D"/>
    <Item Name="Bronze Necklace" Kind="Equipment,Neck" ID="3009"/>
    <Item Name="Golden Amulet" Kind="Equipment,Neck" ID="3013"/>
    <Item Name="Platinum Amulet" Kind="Equipment,Neck" ID="HBEF"/>
    <Item Name="Tempest Rod" Kind="Equipment,SingleHandedWeapon" ID="HBFB"/>
    <Item Name="Moonlight Rod" Kind="Equipment,SingleHandedWeapon" ID="HBFE"/>
    <Item Name="Snakebite Rod" Kind="Equipment,SingleHandedWeapon" ID="HBFA"/>
    <Item Name="Volcanic Rod" Kind="Equipment,SingleHandedWeapon" ID="HBFB"/>
    <Item Name="Quagmire Rod" Kind="Equipment,SingleHandedWeapon" ID="HBF9"/>
    <Item Name="Wand of Vortex" Kind="Equipment,SingleHandedWeapon" ID="HC02"/>
    <Item Name="Wand of Inferno" Kind="Equipment,SingleHandedWeapon" ID="HBFF"/>
    <Item Name="Wand of Plague" Kind="Equipment,SingleHandedWeapon" ID="HC00"/>
    <Item Name="Wand of Cosmic Energy" Kind="Equipment,SingleHandedWeapon" ID="HC01"/>
    <Item Name="Wand of Dragonbreath" Kind="Equipment,SingleHandedWeapon" ID="HC03"/>
    <Item Name="Ring of the Skies" Kind="Equipment,Ring" ID="3006"/>
    <Item Name="Stealth Ring" Kind="Equipment,Ring" ID="HBE9"/>
    <Item Name="Axe Ring" Kind="Equipment,Ring" ID="HC14"/>
    <Item Name="Ring Of Healing" Kind="Equipment,Ring" ID="HC1A"/>
    <Item Name="Life Ring" Kind="Equipment,Ring" ID="HBEC"/>
    <Item Name="Dwarven Ring" Kind="Equipment,Ring" ID="HC19"/>
    <Item Name="Wedding Ring" Kind="Equipment,Ring" ID="HBBC"/>
    <Item Name="Club Ring" Kind="Equipment,Ring" ID="HC15"/>
    <Item Name="Power Ring" Kind="Equipment,Ring" ID="HBEA"/>
    <Item Name="Sword Ring" Kind="Equipment,Ring" ID="HC13"/>
    <Item Name="Time Ring" Kind="Equipment,Ring" ID="HBED"/>
    <Item Name="Crystal Ring" Kind="Equipment,Ring" ID="HBBF"/>
    <Item Name="Energy Ring" Kind="Equipment,Ring" ID="HBEB" />
    <Item Name="Golden Ring" Kind="Equipment,Ring" ID="HBF7"/>
    <Item Name="Bolt" Kind="Equipment,Ammunition" ID="HD76"/>
    <Item Name="Burst Arrow" Kind="Equipment,Ammunition" ID="HD79"/>
    <Item Name="Poison Arrow" Kind="Equipment,Ammunition" ID="HD78"/>
    <Item Name="Arrow" Kind="Equipment,Ammunition" ID="HD77"/>
    <Item Name="Wolf Paw" Kind="Valuable" ID="H1709"/>
    <Item Name="Gold Coin" Kind="Valuable" ID="HBD7"/>
    <Item Name="Honeycomb" Kind="Valuable" ID="H170E"/>
</Items>